PersianG2p/G2P.py
PersianG2p/PersianG2p.py
PersianG2p/__init__.py
PersianG2p/__main__.py
PersianG2p/compares.py
PersianG2p/describe_dictionary.py
PersianG2p/expand.py
PersianG2p/hparams.py
PersianG2p/russian_to_farsi_trans.py
PersianG2p/data/checkpoint.npy
PersianG2p/data/tihudict.dict
PersianG2p/data/tihudict.json
PersianG2p/data/tihudictBIG.json
PersianG2p-0.3.2.dist-info/LICENSE.txt
PersianG2p-0.3.2.dist-info/METADATA
PersianG2p-0.3.2.dist-info/WHEEL
PersianG2p-0.3.2.dist-info/top_level.txt
PersianG2p-0.3.2.dist-info/RECORD
