Metadata-Version: 2.1
Name: PersianG2p
Version: 0.3.2
Summary: Simple grapheme-to-phomene converter for persian (farsi)
Home-page: https://github.com/PasaOpasen/PersianG2P
Author: Demetry Pascal
Author-email: qtckpuhdsa@gmail.com
License: MIT
Download-URL: https://github.com/PasaOpasen/PersianG2P/archive/0.3.1.tar.gz
Keywords: phonemize,g2p,persian,persian_transcription,farsi
Platform: UNKNOWN
Classifier: Development Status :: 3 - Alpha
Classifier: Intended Audience :: Developers
Classifier: Topic :: Software Development :: Build Tools
Classifier: License :: OSI Approved :: MIT License
Classifier: Programming Language :: Python :: 3
Classifier: Programming Language :: Python :: 3.6
Classifier: Programming Language :: Python :: 3.7
Classifier: Programming Language :: Python :: 3.8
Requires-Dist: hazm
Requires-Dist: inflect
Requires-Dist: num2fawords
Requires-Dist: numpy
